challenges/easy/challenge1/README.md
challenges/easy/challenge1/server.py
challenges/easy/challenge1/server_sse.py
challenges/easy/challenge2/README.md
challenges/easy/challenge2/server.py
challenges/easy/challenge2/server_sse.py
challenges/easy/challenge3/README.md
challenges/easy/challenge3/server.py
challenges/easy/challenge3/server_sse.py
challenges/hard/challenge10/README.md
challenges/hard/challenge10/server.py
challenges/hard/challenge10/server_sse.py
challenges/hard/challenge8/README.md
challenges/hard/challenge8/server.py
challenges/hard/challenge8/server_sse.py
challenges/hard/challenge9/README.md
challenges/hard/challenge9/server.py
challenges/hard/challenge9/server_sse.py
challenges/medium/challenge4/README.md
challenges/medium/challenge4/server.py
challenges/medium/challenge4/server_sse.py
challenges/medium/challenge5/README.md
challenges/medium/challenge5/server.py
challenges/medium/challenge5/server_sse.py
challenges/medium/challenge6/README.md
challenges/medium/challenge6/server.py
challenges/medium/challenge6/server_sse.py
challenges/medium/challenge7/README.md
challenges/medium/challenge7/server.py
challenges/medium/challenge7/server_sse.py
common/__init__.py
common/server.py
common/sse_server.py
common/utils.py
iflow_mcp_harishsg993010_damn_vulnerable_mcp_server-0.1.0.dist-info/METADATA
iflow_mcp_harishsg993010_damn_vulnerable_mcp_server-0.1.0.dist-info/WHEEL
iflow_mcp_harishsg993010_damn_vulnerable_mcp_server-0.1.0.dist-info/entry_points.txt
iflow_mcp_harishsg993010_damn_vulnerable_mcp_server-0.1.0.dist-info/RECORD
