Metadata-Version: 2.4
Name: iflow-mcp_harishsg993010_damn-vulnerable-mcp-server
Version: 0.1.0
Summary: Damn Vulnerable MCP - A FastAPI-based MCP challenges project
Author: Your Name
Author-email: you@example.com
Requires-Python: >=3.10,<4.0
Classifier: Programming Language :: Python :: 3
Classifier: Programming Language :: Python :: 3.10
Classifier: Programming Language :: Python :: 3.11
Classifier: Programming Language :: Python :: 3.12
Classifier: Programming Language :: Python :: 3.13
Classifier: Programming Language :: Python :: 3.14
Requires-Dist: fastapi (>=0.95.0)
Requires-Dist: httpx (>=0.24.0)
Requires-Dist: mcp[cli] (>=0.5.0)
Requires-Dist: starlette (>=0.27.0)
Requires-Dist: uvicorn (>=0.21.1)
